actelink/computation.py
actelink/api/__init__.py
actelink/config/__init__.py
actelink/config/settings.py
actelink/logger/__init__.py
actelink/models/__init__.py
actelink/models/utils.py
actelink/server/__init__.py
actelink/server/app.py
actelink_computation-0.5.0.dist-info/LICENSE.txt
actelink_computation-0.5.0.dist-info/METADATA
actelink_computation-0.5.0.dist-info/WHEEL
actelink_computation-0.5.0.dist-info/top_level.txt
actelink_computation-0.5.0.dist-info/RECORD
