Metadata-Version: 2.1
Name: actelink-computation
Version: 0.5.0
Summary: Actelink helpers library for computation management
Author: Actelink
License: LICENSE.txt
Classifier: Programming Language :: Python
Classifier: Programming Language :: Python :: 3
Classifier: Programming Language :: Python :: 3.10
Classifier: License :: OSI Approved :: MIT License
Classifier: Operating System :: OS Independent
Requires-Python: >=3.6
License-File: LICENSE.txt
Requires-Dist: requests
Requires-Dist: flask
Requires-Dist: flask-restx
Requires-Dist: coloredlogs
Requires-Dist: python-dotenv
Requires-Dist: gunicorn
